README.md
setup.py
madlibspy/__init__.py
madlibspy/errors.py
madlibspy/gen.py
madlibspy.egg-info/PKG-INFO
madlibspy.egg-info/SOURCES.txt
madlibspy.egg-info/dependency_links.txt
madlibspy.egg-info/requires.txt
madlibspy.egg-info/top_level.txt