Metadata-Version: 2.1
Name: madlibspy
Version: 2.1
Summary: A library to create your own madlibs game!
Home-page: https://github.com/Nemika-Haj/MadLibsPy
Author: Nemika
Author-email: nemika@bytestobits.dev
License: MIT
Keywords: madlibspy,madlibs,py,python,game,madlibs.py
Platform: UNKNOWN
Classifier: Intended Audience :: Developers
Classifier: Topic :: Software Development :: Build Tools
Classifier: License :: OSI Approved :: MIT License
Classifier: Programming Language :: Python :: 3
Classifier: Programming Language :: Python :: 3.4
Classifier: Programming Language :: Python :: 3.5
Classifier: Programming Language :: Python :: 3.6
Classifier: Programming Language :: Python :: 3.7
Classifier: Programming Language :: Python :: 3.8
Classifier: Programming Language :: Python :: 3.9
